spectrum_analyzer/spectrum_analyzer.srcs/sources_1/new/data_on_trigger.v
`timescale 1ns / 1ps
//////////////////////////////////////////////////////////////////////////////////
// Company: 
// Engineer: 
// 
// Create Date: 08/08/2024 04:01:46 AM
// Design Name: 
// Module Name: data_on_trigger
// Project Name: 
// Target Devices: 
// Tool Versions: 
// Description: 
// Convert Stream data to Packets with trigger
// Wait for rising edge on the trigger 
// Then Transmit data according to the limit
// Dependencies: 
// 
// Revision:
// Revision 0.01 - File Created
// Additional Comments:
// 
//////////////////////////////////////////////////////////////////////////////////


module data_on_trigger#(parameter bW = 32, parameter count_bW = 16, parameter bypass_trigger = 0)(
    input clk,
    input rstn,
    input [bW - 1: 0] s_axi_tdata,
    input s_axi_tvalid,
    input [count_bW - 1:0] maxCount, 
    input trigger,
    output reg [bW - 1: 0] m_axi_tdata,
    output reg m_axi_tvalid,
    output reg m_axi_tlast
    );

    // Rising edge Detector on trigger //
    /////////////////////////////////////
    reg  reg_trigger_1;
    reg  reg_trigger_2;
    wire flag_trigger;
    always@(posedge clk, negedge rstn) begin
        if(~rstn) begin
            reg_trigger_1 <= 1'd0;
            reg_trigger_2 <= 1'd0;
        end 
        else begin
            reg_trigger_1 <= trigger;
            reg_trigger_2 <= reg_trigger_1;
        end
    end
    assign flag_trigger = (bypass_trigger) ? 1'd1 : reg_trigger_1 && (~reg_trigger_2);
    
    // Count Until the End of Limit //
    // Transmit Data accordingly    //
    //////////////////////////////////
    reg [count_bW -1: 0]count;
    reg busy;
    always@(posedge clk, negedge rstn) begin
        if(~rstn) begin
            count <= {count_bW{1'd0}};
            busy <= 1'd0;
            m_axi_tdata <= {bW{1'd0}};
            m_axi_tvalid <= 1'd0;
            m_axi_tlast <= 1'd0;
        end
        else begin// Check if they trigger flag is high or not ? 
            if(count == maxCount - 1'd1) begin
                count <= {count_bW{1'd0}};
                busy <= flag_trigger;
                m_axi_tdata <= s_axi_tdata;
                m_axi_tvalid <= s_axi_tvalid;
                m_axi_tlast <= 1'd1;
            end
            else if (busy == 1'd1) begin
                count <= count + s_axi_tvalid;
                busy <= 1'd1;
                m_axi_tdata <= s_axi_tdata;
                m_axi_tvalid <= s_axi_tvalid;
                m_axi_tlast <= 1'd0;
            end
            else if(flag_trigger == 1'd1) begin
                count <= count;
                busy <= 1'd1;
                m_axi_tdata <= {bW{1'd0}};
                m_axi_tvalid <= 1'd0;
                m_axi_tlast <= 1'd0;
            end
            else begin
                count <= {count_bW{1'd0}};
                busy <= 1'd0;
                m_axi_tdata <= {bW{1'd0}};
                m_axi_tvalid <= 1'd0;
                m_axi_tlast <= 1'd0;
            end
        end
    end
    
endmodule

spectrum_analyzer/spectrum_analyzer.srcs/sources_1/new/tb_data_on_trigger.v
`include "data_on_trigger.v"
`default_nettype none

module tb_data_on_trigger;
// Define Parameters 
parameter bW = 32;
parameter count_bW = 16;
parameter bypass_trigger = 0;

// Define Intermediate Signals
reg clk = 1'd0;
reg rstn = 1'd0;
reg [bW - 1: 0] s_axi_tdata = 0;
reg s_axi_tvalid = 0;
reg [count_bW - 1:0] maxCount = 10;
reg trigger = 0;
wire [bW - 1: 0] m_axi_tdata;
wire m_axi_tvalid;
wire m_axi_tlast;

data_on_trigger #(bW,count_bW,bypass_trigger)
DUT 
(
    .clk(clk),
    .rstn(rstn),
    .s_axi_tdata(s_axi_tdata),
    .s_axi_tvalid(s_axi_tvalid),
    .maxCount(maxCount),
    .trigger(trigger),
    .m_axi_tdata(m_axi_tdata),
    .m_axi_tvalid(m_axi_tvalid),
    .m_axi_tlast(m_axi_tlast)
);

localparam CLK_PERIOD = 10;
always #(CLK_PERIOD/2) clk=~clk;

initial begin
    $dumpfile("tb_data_on_trigger.vcd");
    $dumpvars(0, tb_data_on_trigger);
end

// Input Stimulus
always@(negedge clk) begin
    s_axi_tdata = s_axi_tdata + 1'd1;
    s_axi_tvalid = 1'd1;
end


initial begin
    #1 rstn<=1'b0;clk<=1'b0;
    #(CLK_PERIOD*3) rstn<=1;
    #(CLK_PERIOD*3) rstn<=0;clk<=0;
    repeat(5) @(posedge clk);
    rstn<=1;
    @(posedge clk);
    // Apply trigger 
    trigger <= 1'd1;
    @(posedge clk);
    trigger <= 1'd0;
    // wait for some cycles
    repeat(maxCount + 10) @(posedge clk);
    @(posedge clk);
    // Apply trigger 
    trigger <= 1'd1;
    @(posedge clk);
    trigger <= 1'd0;
    // wait for some cycles
    repeat(maxCount + 10) @(posedge clk);

    repeat(2) @(posedge clk);
    $finish(2);
end

endmodule
`default_nettype wire

spectrum_analyzer/spectrum_analyzer.srcs/sources_1/new/tb_data_on_trigger.vcd
$date
	Fri Aug  9 01:55:07 2024
$end
$version
	Icarus Verilog
$end
$timescale
	1ps
$end
$scope module tb_data_on_trigger $end
$var wire 1 ! m_axi_tvalid $end
$var wire 1 " m_axi_tlast $end
$var wire 32 # m_axi_tdata [31:0] $end
$var reg 1 $ clk $end
$var reg 16 % maxCount [15:0] $end
$var reg 1 & rstn $end
$var reg 32 ' s_axi_tdata [31:0] $end
$var reg 1 ( s_axi_tvalid $end
$var reg 1 ) trigger $end
$scope module DUT $end
$var wire 1 $ clk $end
$var wire 1 * flag_trigger $end
$var wire 16 + maxCount [15:0] $end
$var wire 1 & rstn $end
$var wire 32 , s_axi_tdata [31:0] $end
$var wire 1 ( s_axi_tvalid $end
$var wire 1 ) trigger $end
$var reg 1 - busy $end
$var reg 16 . count [15:0] $end
$var reg 32 / m_axi_tdata [31:0] $end
$var reg 1 " m_axi_tlast $end
$var reg 1 ! m_axi_tvalid $end
$var reg 1 0 reg_trigger_1 $end
$var reg 1 1 reg_trigger_2 $end
$upscope $end
$upscope $end
$enddefinitions $end
#0
$dumpvars
01
00
b0 /
b0 .
0-
b0 ,
b1010 +
0*
0)
0(
b0 '
0&
b1010 %
0$
b0 #
0"
0!
$end
#5000
1$
#10000
1(
b1 '
b1 ,
0$
#15000
1$
#20000
b10 '
b10 ,
0$
#25000
1$
#30000
b11 '
b11 ,
0$
#31000
1&
#35000
1$
#40000
b100 '
b100 ,
0$
#45000
1$
#50000
b101 '
b101 ,
0$
#55000
1$
#60000
b110 '
b110 ,
0$
#61000
0&
#65000
1$
#70000
b111 '
b111 ,
0$
#75000
1$
#80000
b1000 '
b1000 ,
0$
#85000
1$
#90000
b1001 '
b1001 ,
0$
#95000
1$
#100000
b1010 '
b1010 ,
0$
#105000
1&
1$
#110000
b1011 '
b1011 ,
0$
#115000
1)
1$
#120000
b1100 '
b1100 ,
0$
#125000
1*
10
0)
1$
#130000
b1101 '
b1101 ,
0$
#135000
0*
1-
11
00
1$
#140000
b1110 '
b1110 ,
0$
#145000
01
1!
b1110 #
b1110 /
b1 .
1$
#150000
b1111 '
b1111 ,
0$
#155000
b1111 #
b1111 /
b10 .
1$
#160000
b10000 '
b10000 ,
0$
#165000
b10000 #
b10000 /
b11 .
1$
#170000
b10001 '
b10001 ,
0$
#175000
b10001 #
b10001 /
b100 .
1$
#180000
b10010 '
b10010 ,
0$
#185000
b10010 #
b10010 /
b101 .
1$
#190000
b10011 '
b10011 ,
0$
#195000
b10011 #
b10011 /
b110 .
1$
#200000
b10100 '
b10100 ,
0$
#205000
b10100 #
b10100 /
b111 .
1$
#210000
b10101 '
b10101 ,
0$
#215000
b10101 #
b10101 /
b1000 .
1$
#220000
b10110 '
b10110 ,
0$
#225000
b10110 #
b10110 /
b1001 .
1$
#230000
b10111 '
b10111 ,
0$
#235000
1"
b10111 #
b10111 /
0-
b0 .
1$
#240000
b11000 '
b11000 ,
0$
#245000
0"
0!
b0 #
b0 /
1$
#250000
b11001 '
b11001 ,
0$
#255000
1$
#260000
b11010 '
b11010 ,
0$
#265000
1$
#270000
b11011 '
b11011 ,
0$
#275000
1$
#280000
b11100 '
b11100 ,
0$
#285000
1$
#290000
b11101 '
b11101 ,
0$
#295000
1$
#300000
b11110 '
b11110 ,
0$
#305000
1$
#310000
b11111 '
b11111 ,
0$
#315000
1$
#320000
b100000 '
b100000 ,
0$
#325000
1$
#330000
b100001 '
b100001 ,
0$
#335000
1)
1$
#340000
b100010 '
b100010 ,
0$
#345000
1*
10
0)
1$
#350000
b100011 '
b100011 ,
0$
#355000
0*
1-
11
00
1$
#360000
b100100 '
b100100 ,
0$
#365000
01
1!
b100100 #
b100100 /
b1 .
1$
#370000
b100101 '
b100101 ,
0$
#375000
b100101 #
b100101 /
b10 .
1$
#380000
b100110 '
b100110 ,
0$
#385000
b100110 #
b100110 /
b11 .
1$
#390000
b100111 '
b100111 ,
0$
#395000
b100111 #
b100111 /
b100 .
1$
#400000
b101000 '
b101000 ,
0$
#405000
b101000 #
b101000 /
b101 .
1$
#410000
b101001 '
b101001 ,
0$
#415000
b101001 #
b101001 /
b110 .
1$
#420000
b101010 '
b101010 ,
0$
#425000
b101010 #
b101010 /
b111 .
1$
#430000
b101011 '
b101011 ,
0$
#435000
b101011 #
b101011 /
b1000 .
1$
#440000
b101100 '
b101100 ,
0$
#445000
b101100 #
b101100 /
b1001 .
1$
#450000
b101101 '
b101101 ,
0$
#455000
1"
b101101 #
b101101 /
0-
b0 .
1$
#460000
b101110 '
b101110 ,
0$
#465000
0"
0!
b0 #
b0 /
1$
#470000
b101111 '
b101111 ,
0$
#475000
1$
#480000
b110000 '
b110000 ,
0$
#485000
1$
#490000
b110001 '
b110001 ,
0$
#495000
1$
#500000
b110010 '
b110010 ,
0$
#505000
1$
#510000
b110011 '
b110011 ,
0$
#515000
1$
#520000
b110100 '
b110100 ,
0$
#525000
1$
#530000
b110101 '
b110101 ,
0$
#535000
1$
#540000
b110110 '
b110110 ,
0$
#545000
1$
#550000
b110111 '
b110111 ,
0$
#555000
1$
#560000
b111000 '
b111000 ,
0$
